green_igen.libs/libopenblas-r0-f650aae0.3.3.so
green_igen.libs/libgomp-a34b3233.so.1.0.0
green_igen.libs/libgfortran-91cc3cb1.so.3.0.0
green_igen.libs/libquadmath-96973f99.so.0.0.0
green_igen-0.2.7.dist-info/METADATA
green_igen-0.2.7.dist-info/WHEEL
green_igen-0.2.7.dist-info/RECORD
green_igen-0.2.7.dist-info/licenses/LICENSE
green_igen/logger.py
green_igen/linalg_helper.py
green_igen/_vhf.py
green_igen/misc.py
green_igen/libpbc0.so
green_igen/scipy_helper.py
green_igen/__init__.py
green_igen/diis.py
green_igen/exceptions.py
green_igen/outcore.py
green_igen/run.py
green_igen/incore.py
green_igen/numpy_helper.py
green_igen/df.py
green_igen/chkfile.py
green_igen/_pbcintor.py
green_igen/parameters.py
