Metadata-Version: 2.2
Name: green-igen
Version: 0.2.7
Summary: Analytical continuation suits for Green Software Package
Author: Sergei Iskakov
Author-Email: Gaurav Harsha <gharsha@umich.edu>
Classifier: Development Status :: 5 - Production/Stable
Classifier: Programming Language :: Python :: 3
Classifier: License :: OSI Approved :: MIT License
Classifier: Operating System :: POSIX
Classifier: Operating System :: Unix
Classifier: Operating System :: MacOS
Project-URL: Homepage, https://green-phys.org
Project-URL: Issues, https://github.com/Green-Phys/green-igen/issues
Requires-Python: >=3.8
Requires-Dist: numpy
Requires-Dist: h5py
Requires-Dist: scipy
Requires-Dist: pyscf
Provides-Extra: tests
Requires-Dist: coverage>=5.0.3; extra == "tests"
Requires-Dist: pytest; extra == "tests"
Requires-Dist: pytest-benchmark[histogram]>=3.2.1; extra == "tests"
